mlflow_custom_headers_plugin/__init__.py
mlflow_custom_headers_plugin/headers.py
mlflow_custom_headers_plugin-1.0.2.dist-info/LICENSE
mlflow_custom_headers_plugin-1.0.2.dist-info/METADATA
mlflow_custom_headers_plugin-1.0.2.dist-info/WHEEL
mlflow_custom_headers_plugin-1.0.2.dist-info/entry_points.txt
mlflow_custom_headers_plugin-1.0.2.dist-info/top_level.txt
mlflow_custom_headers_plugin-1.0.2.dist-info/RECORD
