Metadata-Version: 2.1
Name: mlflow-custom-headers-plugin
Version: 1.0.2
Summary: MLFlow plugin that allows adding extra headers to requests to MLFlow in order to enable authentication and other use-cases.
Author: Yakko Majuri
Author-email: yakko.majuri@protonmail.com
License: MIT
Project-URL: Source, https://github.com/yakkomajuri/mlflow_custom_headers_plugin
Project-URL: Bug Tracker, https://github.com/yakkomajuri/mlflow_custom_headers_plugin/issues
Requires-Python: >=3.9
License-File: LICENSE
Requires-Dist: mlflow>=2.8.0
